{
  "sharedDir": "shared",
  "dependenciesDir": "extern",
  "info": {
    "name": "playlistmanager",
    "id": "playlistmanager",
    "version": "0.2.1",
    "url": "https://github.com/darknight1050/playlistmanager",
    "additionalData": {
      "soLink": "https://github.com/darknight1050/PlaylistManager/releases/download/v0.2.1/libplaylistmanager.so",
      "debugSoLink": "https://github.com/darknight1050/PlaylistManager/releases/download/v0.2.1/debug_libplaylistmanager.so",
      "overrideSoName": "libplaylistmanager.so",
      "modLink": "https://github.com/darknight1050/PlaylistManager/releases/download/v0.2.1/PlaylistManager.qmod",
      "branchName": "version-v0.2.1"
    }
  },
  "dependencies": [
    {
      "id": "songloader",
      "versionRange": "^0.8.4",
      "additionalData": {}
    },
    {
      "id": "questui",
      "versionRange": "^0.13.2",
      "additionalData": {}
    },
    {
      "id": "codegen",
      "versionRange": "^0.20.0",
      "additionalData": {}
    },
    {
      "id": "custom-types",
      "versionRange": "^0.15.6",
      "additionalData": {}
    },
    {
      "id": "beatsaber-hook",
      "versionRange": "^3.6.7",
      "additionalData": {}
    }
  ],
  "additionalData": {}
}